quinn_image_processing/__init__.py
quinn_image_processing/moveImages.py
quinn_image_processing/movetospecial.py
quinn_image_processing/mvFiles.py
quinn_image_processing/overlayScript.py
quinn_image_processing/removeImages.py
quinn_image_processing/script.py
quinn_image_processing/test_image_overlay.py
quinn_image_processing-3.0.0.dist-info/LICENSE
quinn_image_processing-3.0.0.dist-info/METADATA
quinn_image_processing-3.0.0.dist-info/WHEEL
quinn_image_processing-3.0.0.dist-info/entry_points.txt
quinn_image_processing-3.0.0.dist-info/top_level.txt
quinn_image_processing-3.0.0.dist-info/RECORD
