Metadata-Version: 2.1
Name: quinn_image_processing
Version: 3.0.0
Summary: A simple Python package for image processing.
Home-page: https://github.com/brandonq81/imageprocessing
Author: Brandon Quinn
Author-email: brandonq81@gmail.com
License: MIT
Classifier: Programming Language :: Python :: 3
Classifier: License :: OSI Approved :: MIT License
Classifier: Operating System :: OS Independent
Requires-Python: >=3.9
License-File: LICENSE
Requires-Dist: Pillow >=10.0.0
